zen_garden/__init__.py
zen_garden/__main__.py
zen_garden/default_config.py
zen_garden/optimization_setup.py
zen_garden/runner.py
zen_garden/utils.py
zen_garden/cli/__init__.py
zen_garden/cli/zen_example_cli.py
zen_garden/cli/zen_garden_cli.py
zen_garden/cli/zen_operation_cli.py
zen_garden/cli/zen_visualization_cli.py
zen_garden/model/__init__.py
zen_garden/model/component.py
zen_garden/model/element.py
zen_garden/model/energy_system.py
zen_garden/model/time_steps.py
zen_garden/model/carrier/__init__.py
zen_garden/model/carrier/carrier.py
zen_garden/model/technology/__init__.py
zen_garden/model/technology/conversion_technology.py
zen_garden/model/technology/retrofitting_technology.py
zen_garden/model/technology/storage_technology.py
zen_garden/model/technology/technology.py
zen_garden/model/technology/transport_technology.py
zen_garden/postprocess/.gitkeep
zen_garden/postprocess/__init__.py
zen_garden/postprocess/comparisons.py
zen_garden/postprocess/postprocess.py
zen_garden/postprocess/results/__init__.py
zen_garden/postprocess/results/cache.py
zen_garden/postprocess/results/results.py
zen_garden/postprocess/results/solution_loader.py
zen_garden/preprocess/__init__.py
zen_garden/preprocess/extract_input_data.py
zen_garden/preprocess/parameter_change_log.py
zen_garden/preprocess/time_series_aggregation.py
zen_garden/preprocess/unit_handling.py
zen_garden/wrapper/__init__.py
zen_garden/wrapper/operation_scenarios.py
zen_garden/wrapper/utils.py
zen_garden-2.9.0.dist-info/entry_points.txt
zen_garden-2.9.0.dist-info/licenses/LICENSE.txt
zen_garden-2.9.0.dist-info/WHEEL
zen_garden-2.9.0.dist-info/METADATA
zen_garden-2.9.0.dist-info/RECORD
