Metadata-Version: 2.4
Name: zen_garden
Version: 2.9.0
Summary: ZEN-garden is an optimization model of energy systems and value chains.
Author: Alissa Ganter, Johannes Burger, Francesco De Marco, Lukas Kunz, Lukas Schmidt-Engelbertz, Christoph Funke, Paolo Gabrielli, Giovanni Sansavini
Author-email: Jacob Mannhardt <zen-garden@ethz.ch>
Requires-Python: >=3.11,<3.14
License-File: LICENSE.txt
Requires-Dist: xarray
Requires-Dist: cython
Requires-Dist: numpy
Requires-Dist: pandas<3.0.0
Requires-Dist: scipy
Requires-Dist: pint
Requires-Dist: tables
Requires-Dist: pydantic
Requires-Dist: tsam
Requires-Dist: h5py
Requires-Dist: filelock
Requires-Dist: ordered-set
Requires-Dist: pyogrio
Requires-Dist: psutil
Requires-Dist: linopy
Requires-Dist: requests
Requires-Dist: ipykernel
Requires-Dist: zen-temple>=0.7.3
Requires-Dist: pytest ; extra == "dev"
Requires-Dist: coverage ; extra == "dev"
Requires-Dist: pytest-xdist ; extra == "dev"
Requires-Dist: pytest-cov ; extra == "dev"
Requires-Dist: black==25.12.0 ; extra == "dev"
Requires-Dist: ruff==0.14.13 ; extra == "dev"
Requires-Dist: mypy==1.19.1 ; extra == "dev"
Requires-Dist: sphinx==7.3.7 ; extra == "docs"
Requires-Dist: myst-parser==3.0.1 ; extra == "docs"
Requires-Dist: sphinx-book-theme==1.1.3 ; extra == "docs"
Requires-Dist: pydata-sphinx-theme==0.15.4 ; extra == "docs"
Requires-Dist: sphinx-reredirects==0.1.4 ; extra == "docs"
Requires-Dist: nbsphinx==0.9.4 ; extra == "docs"
Requires-Dist: nbsphinx-link==1.3.0 ; extra == "docs"
Requires-Dist: sphinxcontrib-mermaid ; extra == "docs"
Requires-Dist: furo ; extra == "docs"
Requires-Dist: gurobipy ; extra == "gurobipy"
Requires-Dist: matplotlib ; extra == "vis"
Project-URL: Documentation, https://zen-garden.readthedocs.io/en/latest/
Project-URL: Homepage, https://github.com/ZEN-universe/ZEN-garden
Project-URL: Zenodo, https://zenodo.org/api/records/13385110
Provides-Extra: dev
Provides-Extra: docs
Provides-Extra: gurobipy
Provides-Extra: vis
